<?xml version="1.0" encoding="UTF-8"?>
<root>
  <logInfo1409914061>
    <timestamp>05.09.2014 14:47:41</timestamp>
    <webpage>http://ust-co.ru/arenda/skladskaya-tekhnika/</webpage>
    <responsecode>200</responsecode>
  </logInfo1409914061>
  <logInfo1409924259>
    <timestamp>05.09.2014 17:37:39</timestamp>
    <webpage>http://ust-co.ru/filialy/tula/</webpage>
    <responsecode>200</responsecode>
  </logInfo1409924259>
  <logInfo1409934091>
    <timestamp>05.09.2014 20:21:31</timestamp>
    <webpage>http://ust-co.ru/</webpage>
    <responsecode>200</responsecode>
  </logInfo1409934091>
</root>
