<?xml version="1.0" encoding="UTF-8"?>
<root>
  <logInfo1409827351>
    <timestamp>04.09.2014 14:42:31</timestamp>
    <webpage>http://u-st.ru/catalog/avtogreydery/avtogreyder-john-deere-672g/</webpage>
    <responsecode>200</responsecode>
  </logInfo1409827351>
  <logInfo1409827400>
    <timestamp>04.09.2014 14:43:20</timestamp>
    <webpage>http://u-st.ru/catalog/avtogreydery/?utm_source=yandex&amp;utm_medium=cpc&amp;utm_campaign=john_deere_avtogreyderi_rossiya&amp;utm_content=avtogreyder</webpage>
    <responsecode>200</responsecode>
  </logInfo1409827400>
</root>
