<?xml version="1.0" encoding="UTF-8"?>
<root>
  <logInfo1409907781>
    <timestamp>05.09.2014 13:03:01</timestamp>
    <webpage>http://u-st.ru/catalog/gusenichnye-samosvaly/gusenichnyy-samosval-mst-800vd/</webpage>
    <responsecode>200</responsecode>
  </logInfo1409907781>
  <logInfo1409907800>
    <timestamp>05.09.2014 13:03:20</timestamp>
    <webpage>http://u-st.ru/catalog/podemniki/</webpage>
    <responsecode>200</responsecode>
  </logInfo1409907800>
  <logInfo1409907804>
    <timestamp>05.09.2014 13:03:24</timestamp>
    <webpage>http://u-st.ru/catalog/burovoe-i-svaeboynoe-oborudovanie/</webpage>
    <responsecode>200</responsecode>
  </logInfo1409907804>
  <logInfo1409907806>
    <timestamp>05.09.2014 13:03:26</timestamp>
    <webpage>http://u-st.ru/catalog/mini-ekskavatory/</webpage>
    <responsecode>200</responsecode>
  </logInfo1409907806>
  <logInfo1409907813>
    <timestamp>05.09.2014 13:03:33</timestamp>
    <webpage>http://u-st.ru/akcii/stroitelnaya-tekhnika/poprobuy-i-kupi-lyubaya-tekhnika-v-arendu-s-vykupom/</webpage>
    <responsecode>404</responsecode>
  </logInfo1409907813>
  <logInfo1409907846>
    <timestamp>05.09.2014 13:04:06</timestamp>
    <webpage>http://u-st.ru/catalog/bu-stroitelnaya-tehnika/</webpage>
    <responsecode>200</responsecode>
  </logInfo1409907846>
</root>
