<?xml version="1.0" encoding="UTF-8"?>
<root>
  <logInfo1409807045>
    <timestamp>04.09.2014 09:04:05</timestamp>
    <webpage>http://u-st.ru/catalog/grokhoty-mobilnye/grokhot-mobilnyy-vtorichnyy-parker-sd225/</webpage>
    <responsecode>200</responsecode>
  </logInfo1409807045>
  <logInfo1409807086>
    <timestamp>04.09.2014 09:04:46</timestamp>
    <webpage>http://u-st.ru/catalog/grokhoty-polumobilnye/</webpage>
    <responsecode>200</responsecode>
  </logInfo1409807086>
  <logInfo1409807092>
    <timestamp>04.09.2014 09:04:52</timestamp>
    <webpage>http://u-st.ru/catalog/grokhoty-polumobilnye/grokhot-polumobilnyy-barabannyy-smi-612w/</webpage>
    <responsecode>200</responsecode>
  </logInfo1409807092>
  <logInfo1409807226>
    <timestamp>04.09.2014 09:07:06</timestamp>
    <webpage>http://u-st.ru/catalog/spetspredlozheniya-dso/</webpage>
    <responsecode>200</responsecode>
  </logInfo1409807226>
  <logInfo1409807336>
    <timestamp>04.09.2014 09:08:56</timestamp>
    <webpage>http://u-st.ru/arenda/stroitelnaya-tekhnika/</webpage>
    <responsecode>200</responsecode>
  </logInfo1409807336>
  <logInfo1409807389>
    <timestamp>04.09.2014 09:09:49</timestamp>
    <webpage>http://ust-co.ru/arenda/skladskaya-tekhnika/</webpage>
    <responsecode>200</responsecode>
  </logInfo1409807389>
  <logInfo1409807402>
    <timestamp>04.09.2014 09:10:02</timestamp>
    <webpage>http://u-st.ru/catalog/drobilno-sortirovochnoe-oborudovanie/</webpage>
    <responsecode>200</responsecode>
  </logInfo1409807402>
  <logInfo1409807432>
    <timestamp>04.09.2014 09:10:32</timestamp>
    <webpage>http://u-st.ru/ajax/filter_new.php</webpage>
    <responsecode>200</responsecode>
  </logInfo1409807432>
  <logInfo1409807435>
    <timestamp>04.09.2014 09:10:35</timestamp>
    <webpage>http://u-st.ru/catalog/grokhoty-mobilnye/</webpage>
    <responsecode>200</responsecode>
  </logInfo1409807435>
  <logInfo1409807452>
    <timestamp>04.09.2014 09:10:52</timestamp>
    <webpage>http://u-st.ru/ajax/filter_new.php</webpage>
    <responsecode>200</responsecode>
  </logInfo1409807452>
  <logInfo1409807454>
    <timestamp>04.09.2014 09:10:54</timestamp>
    <webpage>http://u-st.ru/catalog/grokhoty-polumobilnye/</webpage>
    <responsecode>200</responsecode>
  </logInfo1409807454>
  <logInfo1409807472>
    <timestamp>04.09.2014 09:11:12</timestamp>
    <webpage>http://u-st.ru/catalog/grokhoty-polumobilnye/grokhot-mobilnyy-barabannyy-smi-612t/</webpage>
    <responsecode>200</responsecode>
  </logInfo1409807472>
  <logInfo1409807508>
    <timestamp>04.09.2014 09:11:48</timestamp>
    <webpage>http://u-st.ru/catalog/grokhoty-polumobilnye/</webpage>
    <responsecode>200</responsecode>
  </logInfo1409807508>
  <logInfo1409807512>
    <timestamp>04.09.2014 09:11:52</timestamp>
    <webpage>http://u-st.ru/catalog/grokhoty-polumobilnye/grokhot-polumobilnyy-barabannyy-smi-612w/</webpage>
    <responsecode>200</responsecode>
  </logInfo1409807512>
  <logInfo1409807531>
    <timestamp>04.09.2014 09:12:11</timestamp>
    <webpage>http://u-st.ru/filialy/voronezh/</webpage>
    <responsecode>200</responsecode>
  </logInfo1409807531>
  <logInfo1409807576>
    <timestamp>04.09.2014 09:12:56</timestamp>
    <webpage>http://ust-co.ru/partnery/sertifikaty/</webpage>
    <responsecode>200</responsecode>
  </logInfo1409807576>
  <logInfo1409807579>
    <timestamp>04.09.2014 09:12:59</timestamp>
    <webpage>http://ust-co.ru/catalog/zakupka/</webpage>
    <responsecode>200</responsecode>
  </logInfo1409807579>
  <logInfo1409807599>
    <timestamp>04.09.2014 09:13:19</timestamp>
    <webpage>http://generatory.ust-co.ru/catalog/generatory/</webpage>
    <responsecode>200</responsecode>
  </logInfo1409807599>
  <logInfo1409807619>
    <timestamp>04.09.2014 09:13:39</timestamp>
    <webpage>http://ust-co.ru/servis/zapchasti-i-komplektuyushie/</webpage>
    <responsecode>200</responsecode>
  </logInfo1409807619>
  <logInfo1409807627>
    <timestamp>04.09.2014 09:13:47</timestamp>
    <webpage>http://u-st.ru/catalog/mobilnye-krany/</webpage>
    <responsecode>200</responsecode>
  </logInfo1409807627>
  <logInfo1409807631>
    <timestamp>04.09.2014 09:13:51</timestamp>
    <webpage>http://u-st.ru/catalog/drobilno-sortirovochnoe-oborudovanie/</webpage>
    <responsecode>200</responsecode>
  </logInfo1409807631>
</root>
