<?xml version="1.0" encoding="UTF-8"?>
<root>
  <logInfo1409825493>
    <timestamp>04.09.2014 14:11:33</timestamp>
    <webpage>http://ust-co.ru/design/img/css/transparent.png</webpage>
    <responsecode>404</responsecode>
  </logInfo1409825493>
  <logInfo1409825513>
    <timestamp>04.09.2014 14:11:53</timestamp>
    <webpage>http://u-st.ru/catalog/mini-pogruzchiki/</webpage>
    <responsecode>200</responsecode>
  </logInfo1409825513>
  <logInfo1409825516>
    <timestamp>04.09.2014 14:11:56</timestamp>
    <webpage>http://ust-co.ru/design/img/css/transparent.png</webpage>
    <responsecode>404</responsecode>
  </logInfo1409825516>
  <logInfo1409825528>
    <timestamp>04.09.2014 14:12:08</timestamp>
    <webpage>http://u-st.ru/catalog/mini-pogruzchiki/mini-pogruzchik-john-deere-313/</webpage>
    <responsecode>200</responsecode>
  </logInfo1409825528>
  <logInfo1409825532>
    <timestamp>04.09.2014 14:12:12</timestamp>
    <webpage>http://ust-co.ru/design/img/css/transparent.png</webpage>
    <responsecode>404</responsecode>
  </logInfo1409825532>
</root>
