<?xml version="1.0" encoding="UTF-8"?>
<root>
  <logInfo1409898331>
    <timestamp>05.09.2014 10:25:31</timestamp>
    <webpage>http://ust-co.ru/catalog/gidravlicheskie-shtabelery/?utm_source=yandex&amp;utm_medium=cpc&amp;utm_campaign=unilift_rossiya&amp;utm_content=..ruchnoy_gidravlicheskiy_shtabeler..</webpage>
    <responsecode>200</responsecode>
  </logInfo1409898331>
  <logInfo1409898350>
    <timestamp>05.09.2014 10:25:50</timestamp>
    <webpage>http://ust-co.ru/catalog/gidravlicheskie-shtabelery/gidravlicheskiy-shtabeler-unilift-shm-1516n/</webpage>
    <responsecode>200</responsecode>
  </logInfo1409898350>
</root>
