<?xml version="1.0" encoding="UTF-8"?>
<root>
  <logInfo1409985089>
    <timestamp>06.09.2014 10:31:29</timestamp>
    <webpage>http://ust-co.ru/catalog/gidravlicheskie-telezhki/ruchnaya-gidravlicheskaya-telezhka-unilift-th-u-universal/</webpage>
    <responsecode>200</responsecode>
  </logInfo1409985089>
  <logInfo1409985107>
    <timestamp>06.09.2014 10:31:47</timestamp>
    <webpage>http://ust-co.ru/filialy/</webpage>
    <responsecode>200</responsecode>
  </logInfo1409985107>
  <logInfo1409985190>
    <timestamp>06.09.2014 10:33:10</timestamp>
    <webpage>http://ust-co.ru/catalog/vilochnye-pogruzchiki/</webpage>
    <responsecode>200</responsecode>
  </logInfo1409985190>
  <logInfo1409985192>
    <timestamp>06.09.2014 10:33:12</timestamp>
    <webpage>http://ust-co.ru/catalog/vilochnye-pogruzchiki/</webpage>
    <responsecode>200</responsecode>
  </logInfo1409985192>
  <logInfo1409985194>
    <timestamp>06.09.2014 10:33:14</timestamp>
    <webpage>http://ust-co.ru/catalog/gidravlicheskie-telezhki/</webpage>
    <responsecode>200</responsecode>
  </logInfo1409985194>
</root>
