<?xml version="1.0" encoding="UTF-8"?>
<root>
  <logInfo1409919136>
    <timestamp>05.09.2014 16:12:16</timestamp>
    <webpage>http://ust-co.ru/%D0%9A%D0%B0%D1%80%D1%8C%D0%B5%D1%80%D0%BD%D1%8B%D0%B5%20%D1%81%D0%B0%D0%BC%D0%BE%D1%81%D0%B2%D0%B0%D0%BB%D1%8B%20John%20Deere%20%D0%B2%20%D1%80%D0%B0%D0%B1%D0%BE%D1%82%D0%B5</webpage>
    <responsecode>404</responsecode>
  </logInfo1409919136>
  <logInfo1409919144>
    <timestamp>05.09.2014 16:12:24</timestamp>
    <webpage>http://u-st.ru/catalog/drobilno-sortirovochnoe-oborudovanie/</webpage>
    <responsecode>200</responsecode>
  </logInfo1409919144>
  <logInfo1409919155>
    <timestamp>05.09.2014 16:12:35</timestamp>
    <webpage>http://u-st.ru/catalog/stroitelnaya-tekhnika/</webpage>
    <responsecode>200</responsecode>
  </logInfo1409919155>
  <logInfo1409919167>
    <timestamp>05.09.2014 16:12:47</timestamp>
    <webpage>http://u-st.ru/o-kompanii/statyi/stroitelnaya-tekhnika/v-rossiyu-my-prishli-vseryez-i-nadolgo-press-zavtrak-s-john-deere/</webpage>
    <responsecode>200</responsecode>
  </logInfo1409919167>
  <logInfo1409919279>
    <timestamp>05.09.2014 16:14:39</timestamp>
    <webpage>http://ust-co.ru/o-kompanii/otzyvy/</webpage>
    <responsecode>200</responsecode>
  </logInfo1409919279>
  <logInfo1409919333>
    <timestamp>05.09.2014 16:15:33</timestamp>
    <webpage>http://u-st.ru/catalog/stroitelnaya-tekhnika/</webpage>
    <responsecode>200</responsecode>
  </logInfo1409919333>
</root>
