<?xml version="1.0" encoding="UTF-8"?>
<root>
  <logInfo1409909557>
    <timestamp>05.09.2014 13:32:37</timestamp>
    <webpage>http://u-st.ru/ajax/filter_new.php</webpage>
    <responsecode>200</responsecode>
  </logInfo1409909557>
  <logInfo1409909563>
    <timestamp>05.09.2014 13:32:43</timestamp>
    <webpage>http://u-st.ru/catalog/teleskopicheskie-pogruzchiki/</webpage>
    <responsecode>200</responsecode>
  </logInfo1409909563>
  <logInfo1409909614>
    <timestamp>05.09.2014 13:33:34</timestamp>
    <webpage>http://u-st.ru/catalog/teleskopicheskie-pogruzchiki/?view_page=list</webpage>
    <responsecode>200</responsecode>
  </logInfo1409909614>
  <logInfo1409909643>
    <timestamp>05.09.2014 13:34:03</timestamp>
    <webpage>http://u-st.ru/catalog/teleskopicheskie-pogruzchiki/?quantity=10000</webpage>
    <responsecode>200</responsecode>
  </logInfo1409909643>
</root>
